lamarr_energy_tracker/__init__.py
lamarr_energy_tracker/print_paper_statement.py
lamarr_energy_tracker/tracker.py
lamarr_energy_tracker-0.1.0.dist-info/METADATA
lamarr_energy_tracker-0.1.0.dist-info/WHEEL
lamarr_energy_tracker-0.1.0.dist-info/top_level.txt
lamarr_energy_tracker-0.1.0.dist-info/RECORD
