Metadata-Version: 2.4
Name: lamarr-energy-tracker
Version: 0.1.0
Summary: A CodeCarbon wrapper for tracking and reporting energy consumption of ML experiments
Home-page: https://github.com/lamarr-institute/lamarr-energy-tracker
Author: Resource-aware ML Research Team @ Lamarr Institute
Author-email: sebastian.buschjaeger@tu-dortmund.de
Classifier: Development Status :: 3 - Alpha
Classifier: Intended Audience :: Science/Research
Classifier: License :: OSI Approved :: MIT License
Classifier: Operating System :: OS Independent
Classifier: Programming Language :: Python :: 3
Classifier: Programming Language :: Python :: 3.8
Classifier: Programming Language :: Python :: 3.9
Classifier: Programming Language :: Python :: 3.10
Classifier: Programming Language :: Python :: 3.11
Requires-Python: >=3.8
Requires-Dist: codecarbon==3.0.8
Requires-Dist: argparse
Provides-Extra: test
Requires-Dist: pytest>=7.0.0; extra == "test"
Requires-Dist: pandas>=1.0.0; extra == "test"
Dynamic: author
Dynamic: author-email
Dynamic: classifier
Dynamic: description
Dynamic: description-content-type
Dynamic: home-page
Dynamic: provides-extra
Dynamic: requires-dist
Dynamic: requires-python
Dynamic: summary
